<?xml version="1.0" encoding="utf-8"?>
<publishData>
  <publishProfile publishUrl="D:\WORK\Trademaster\publish" deleteExistingFiles="True" ftpAnonymousLogin="False" ftpPassiveMode="True" msdeploySite="" msdeploySiteID="" msdeployRemoteSitePhysicalPath="" msdeployAllowUntrustedCertificate="False" msdeploySkipExtraFilesOnServer="True" msdeployMarkAsApp="False" profileName="Profile1" publishMethod="FileSystem" replaceMatchingFiles="False" userName="" savePWD="False" userPWD="" SelectedForPublish="True">
    <file relUrl="LIB/TM.Objects.pdb" publishTime="08/13/2012 18:55:56" />
    <file relUrl="Rule.aspx.cs" publishTime="07/20/2012 16:44:44" />
    <file relUrl="LIB/CodeEffects.Rule.dll" publishTime="07/17/2012 18:09:22" />
    <file relUrl="LIB/Microsoft.Practices.EnterpriseLibrary.Data.dll" publishTime="10/01/2011 14:32:30" />
    <file relUrl="LIB/Microsoft.Practices.EnterpriseLibrary.Common.dll" publishTime="10/01/2011 14:32:30" />
    <file relUrl="Styles/Site.css" publishTime="07/07/2012 13:01:44" />
    <file relUrl="bin/CodeEffects.Rule.xml" publishTime="03/26/2012 20:18:32" />
    <file relUrl="Global.asax.cs" publishTime="07/07/2012 13:01:54" />
    <file relUrl="bin/TA-Lib-Core.dll" publishTime="09/07/2011 21:05:30" />
    <file relUrl="bin/TM.Objects.pdb" publishTime="08/13/2012 18:55:56" />
    <file relUrl="Global.asax" publishTime="07/07/2012 13:01:48" />
    <file relUrl="LIB/CodeEffects.Rule.xml" publishTime="03/26/2012 20:18:32" />
    <file relUrl="RuleResults.aspx.designer.cs" publishTime="08/16/2012 20:03:58" />
    <file relUrl="Properties/AssemblyInfo.cs" publishTime="07/17/2012 19:30:24" />
    <file relUrl="Common/ProcessingResult.cs" publishTime="02/08/2012 20:32:44" />
    <file relUrl="bin/TM.DAL.dll" publishTime="08/13/2012 18:55:56" />
    <file relUrl="LIB/TM.DAL.dll" publishTime="08/13/2012 18:55:56" />
    <file relUrl="TM.Rules.Web.csproj" publishTime="09/02/2012 19:28:04" />
    <file relUrl="Common/Common.css" publishTime="07/19/2012 12:58:36" />
    <file relUrl="Scripts/jquery-1.4.1.min.js" publishTime="07/07/2012 13:01:48" />
    <file relUrl="bin/TM.Objects.dll" publishTime="08/13/2012 18:55:56" />
    <file relUrl="LIB/TM.DAL.pdb" publishTime="08/13/2012 18:55:56" />
    <file relUrl="About.aspx" publishTime="09/02/2012 12:45:07" />
    <file relUrl="Scripts/jquery-1.4.1.js" publishTime="07/07/2012 13:01:48" />
    <file relUrl="DefineRules.aspx.cs" publishTime="08/17/2012 17:57:58" />
    <file relUrl="LIB/TA-Lib-Core.dll" publishTime="09/07/2011 21:05:30" />
    <file relUrl="About.aspx.cs" publishTime="07/07/2012 13:01:48" />
    <file relUrl="Scripts/jquery-1.4.1-vsdoc.js" publishTime="07/07/2012 13:01:48" />
    <file relUrl="Site.Master.designer.cs" publishTime="07/20/2012 16:18:40" />
    <file relUrl="About.aspx.designer.cs" publishTime="07/07/2012 13:01:48" />
    <file relUrl="Site.Master" publishTime="09/02/2012 19:30:46" />
    <file relUrl="bin/Microsoft.Practices.EnterpriseLibrary.Data.dll" publishTime="10/01/2011 14:32:30" />
    <file relUrl="RuleResults.aspx.cs" publishTime="08/17/2012 17:38:30" />
    <file relUrl="bin/Microsoft.Practices.EnterpriseLibrary.Common.dll" publishTime="10/01/2011 14:32:30" />
    <file relUrl="bin/CodeEffects.Rule.dll" publishTime="07/17/2012 18:09:22" />
    <file relUrl="LIB/Interop.EgarDDSEnt.dll" publishTime="07/07/2012 13:01:54" />
    <file relUrl="DefineRules.aspx.designer.cs" publishTime="08/17/2012 17:57:20" />
    <file relUrl="bin/TM.DAL.pdb" publishTime="08/13/2012 18:55:56" />
    <file relUrl="LIB/TM.Objects.dll" publishTime="08/13/2012 18:55:56" />
    <file relUrl="Images/HomeImage.png" publishTime="07/20/2012 16:42:44" />
    <file relUrl="Site.Master.cs" publishTime="07/07/2012 13:01:54" />
    <file relUrl="TM.Rules.Web.csproj.user" publishTime="09/02/2012 19:28:04" />
    <file relUrl="Rule.aspx.designer.cs" publishTime="07/20/2012 16:40:36" />
    <file relUrl="DefineRules.aspx" publishTime="08/17/2012 17:57:24" />
    <file relUrl="bin/TM.Rules.Web.pdb" publishTime="09/02/2012 19:28:09" />
    <file relUrl="bin/TM.Rules.Web.dll" publishTime="09/02/2012 19:28:10" />
    <file relUrl="RuleResults.aspx" publishTime="08/17/2012 17:55:08" />
    <file relUrl="Rules/Rule.config" publishTime="07/07/2012 13:01:48" />
    <file relUrl="Common/CustomHelpFile.config" publishTime="02/28/2012 20:29:56" />
    <file relUrl="Common/Storage.cs" publishTime="03/25/2012 20:45:54" />
    <file relUrl="Rule.aspx" publishTime="09/02/2012 19:27:58" />
    <file relUrl="Web.config" publishTime="09/02/2012 12:35:40" />
  </publishProfile>
</publishData>